nose2_kflag/__init__.py
nose2_kflag/testnamepatterns.py
nose2_kflag/tests/__init__.py
nose2_kflag/tests/test_doctests.py
nose2_kflag/tests/test_functions.py
nose2_kflag/tests/test_generators.py
nose2_kflag/tests/test_loadtests.py
nose2_kflag/tests/test_such.py
nose2_kflag/tests/test_unittests.py
nose2_kflag-1.0.dist-info/LICENSE
nose2_kflag-1.0.dist-info/METADATA
nose2_kflag-1.0.dist-info/WHEEL
nose2_kflag-1.0.dist-info/top_level.txt
nose2_kflag-1.0.dist-info/zip-safe
nose2_kflag-1.0.dist-info/RECORD
