Metadata-Version: 2.1
Name: nose2-kflag
Version: 1.0
Summary: nose2 plugin to only run tests which match a given substring
Home-page: https://github.com/stefanholek/nose2-kflag
Author: Stefan H. Holek
Author-email: stefan@epy.co.at
License: BSD-2-Clause
Project-URL: Bug Tracker, https://github.com/stefanholek/nose2-kflag/issues
Project-URL: Source Code, https://github.com/stefanholek/nose2-kflag
Keywords: nose2 plugin kflag test-name-pattern patterns filter
Platform: UNKNOWN
Classifier: Development Status :: 5 - Production/Stable
Classifier: Intended Audience :: Developers
Classifier: License :: OSI Approved :: BSD License
Classifier: Operating System :: OS Independent
Classifier: Programming Language :: Python
Classifier: Programming Language :: Python :: 2
Classifier: Programming Language :: Python :: 3
Requires-Dist: nose2
